{"id":321,"name":"wailord","order":432,"height":145,"weight":3980,"baseExp":175,"default":true,"versions":["ruby","sapphire","emerald","firered","leafgreen","diamond","pearl","platinum","heartgold","soulsilver","black","white","black-2","white-2"],"types":["water"],"images":{"thumbRegular":"api/pokemon/321.thumbRegular.png","thumbShiny":"api/pokemon/321.thumbShiny.png","largeRegular":"api/pokemon/321.largeRegular.png","largeShiny":"api/pokemon/321.largeShiny.png"},"stats":[{"name":"hp","base":170,"effort":2},{"name":"attack","base":90,"effort":0},{"name":"defense","base":45,"effort":0},{"name":"special-attack","base":90,"effort":0},{"name":"special-defense","base":45,"effort":0},{"name":"speed","base":60,"effort":0}],"abilities":[{"name":"water-veil","hidden":false},{"name":"oblivious","hidden":false},{"name":"pressure","hidden":true}],"moves":[{"name":"headbutt","versions":[{"version":"heartgold-soulsilver","method":"tutor","level":0}]},{"name":"body-slam","versions":[{"version":"emerald","method":"tutor","level":0},{"version":"firered-leafgreen","method":"tutor","level":0},{"version":"xd","method":"tutor","level":0},{"version":"sword-shield","method":"level-up","level":36},{"version":"sword-shield","method":"machine","level":0}]},{"name":"double-edge","versions":[{"version":"emerald","method":"tutor","level":0},{"version":"firered-leafgreen","method":"tutor","level":0},{"version":"xd","method":"tutor","level":0}]},{"name":"growl","versions":[{"version":"ruby-sapphire","method":"level-up","level":1},{"version":"ruby-sapphire","method":"level-up","level":5},{"version":"emerald","method":"level-up","level":1},{"version":"emerald","method":"level-up","level":5},{"version":"firered-leafgreen","method":"level-up","level":1},{"version":"firered-leafgreen","method":"level-up","level":5},{"version":"diamond-pearl","method":"level-up","level":1},{"version":"diamond-pearl","method":"level-up","level":4},{"version":"platinum","method":"level-up","level":1},{"version":"platinum","method":"level-up","level":4},{"version":"heartgold-soulsilver","method":"level-up","level":1},{"version":"heartgold-soulsilver","method":"level-up","level":4},{"version":"black-white","method":"level-up","level":1},{"version":"black-white","method":"level-up","level":4},{"version":"colosseum","method":"level-up","level":1},{"version":"colosseum","method":"level-up","level":5},{"version":"xd","method":"level-up","level":1},{"version":"xd","method":"level-up","level":5},{"version":"black-2-white-2","method":"level-up","level":1},{"version":"black-2-white-2","method":"level-up","level":4},{"version":"x-y","method":"level-up","level":1},{"version":"x-y","method":"level-up","level":4},{"version":"omega-ruby-alpha-sapphire","method":"level-up","level":1},{"version":"omega-ruby-alpha-sapphire","method":"level-up","level":4},{"version":"sun-moon","method":"level-up","level":1},{"version":"sun-moon","method":"level-up","level":4},{"version":"ultra-sun-ultra-moon","method":"level-up","level":1},{"version":"ultra-sun-ultra-moon","method":"level-up","level":4},{"version":"sword-shield","method":"level-up","level":1}]},{"name":"roar","versions":[{"version":"ruby-sapphire","method":"machine","level":0},{"version":"emerald","method":"machine","level":0},{"version":"firered-leafgreen","method":"machine","level":0},{"version":"diamond-pearl","method":"machine","level":0},{"version":"platinum","method":"machine","level":0},{"version":"heartgold-soulsilver","method":"machine","level":0},{"version":"black-white","method":"machine","level":0},{"version":"colosseum","method":"machine","level":0},{"version":"xd","method":"machine","level":0},{"version":"black-2-white-2","method":"machine","level":0},{"version":"x-y","method":"machine","level":0},{"version":"omega-ruby-alpha-sapphire","method":"machine","level":0},{"version":"sun-moon","method":"machine","level":0},{"version":"ultra-sun-ultra-moon","method":"machine","level":0}]},{"name":"mist","versions":[{"version":"ruby-sapphire","method":"level-up","level":32},{"version":"emerald","method":"level-up","level":32},{"version":"firered-leafgreen","method":"level-up","level":32},{"version":"diamond-pearl","method":"level-up","level":24},{"version":"platinum","method":"level-up","level":24},{"version":"heartgold-soulsilver","method":"level-up","level":24},{"version":"black-white","method":"level-up","level":24},{"version":"colosseum","method":"level-up","level":32},{"version":"xd","method":"level-up","level":32},{"version":"black-2-white-2","method":"level-up","level":24},{"version":"x-y","method":"level-up","level":24},{"version":"omega-ruby-alpha-sapphire","method":"level-up","level":22},{"version":"sun-moon","method":"level-up","level":22},{"version":"ultra-sun-ultra-moon","method":"level-up","level":22},{"version":"sword-shield","method":"level-up","level":15}]},{"name":"water-gun","versions":[{"version":"ruby-sapphire","method":"level-up","level":1},{"version":"ruby-sapphire","method":"level-up","level":10},{"version":"emerald","method":"level-up","level":1},{"version":"emerald","method":"level-up","level":10},{"version":"firered-leafgreen","method":"level-up","level":1},{"version":"firered-leafgreen","method":"level-up","level":10},{"version":"diamond-pearl","method":"level-up","level":1},{"version":"diamond-pearl","method":"level-up","level":7},{"version":"platinum","method":"level-up","level":1},{"version":"platinum","method":"level-up","level":7},{"version":"heartgold-soulsilver","method":"level-up","level":1},{"version":"heartgold-soulsilver","method":"level-up","level":7},{"version":"black-white","method":"level-up","level":1},{"version":"black-white","method":"level-up","level":7},{"version":"colosseum","method":"level-up","level":1},{"version":"colosseum","method":"level-up","level":10},{"version":"xd","method":"level-up","level":1},{"version":"xd","method":"level-up","level":10},{"version":"black-2-white-2","method":"level-up","level":1},{"version":"black-2-white-2","method":"level-up","level":7},{"version":"x-y","method":"level-up","level":1},{"version":"x-y","method":"level-up","level":7},{"version":"omega-ruby-alpha-sapphire","method":"level-up","level":1},{"version":"omega-ruby-alpha-sapphire","method":"level-up","level":7},{"version":"sun-moon","method":"level-up","level":1},{"version":"sun-moon","method":"level-up","level":7},{"version":"ultra-sun-ultra-moon","method":"level-up","level":1},{"version":"ultra-sun-ultra-moon","method":"level-up","level":7},{"version":"sword-shield","method":"level-up","level":1}]},{"name":"hydro-pump","versions":[{"version":"ruby-sapphire","method":"level-up","level":59},{"version":"emerald","method":"level-up","level":59},{"version":"firered-leafgreen","method":"level-up","level":59},{"version":"diamond-pearl","method":"level-up","level":62},{"version":"platinum","method":"level-up","level":62},{"version":"heartgold-soulsilver","method":"level-up","level":62},{"version":"black-white","method":"level-up","level":62},{"version":"colosseum","method":"level-up","level":59},{"version":"xd","method":"level-up","level":59},{"version":"black-2-white-2","method":"level-up","level":62},{"version":"x-y","method":"level-up","level":62},{"version":"omega-ruby-alpha-sapphire","method":"level-up","level":58},{"version":"sun-moon","method":"level-up","level":58},{"version":"ultra-sun-ultra-moon","method":"level-up","level":58},{"version":"sword-shield","method":"level-up","level":49},{"version":"sword-shield","method":"machine","level":0}]},{"name":"surf","versions":[{"version":"ruby-sapphire","method":"machine","level":0},{"version":"emerald","method":"machine","level":0},{"version":"firered-leafgreen","method":"machine","level":0},{"version":"diamond-pearl","method":"machine","level":0},{"version":"platinum","method":"machine","level":0},{"version":"heartgold-soulsilver","method":"machine","level":0},{"version":"black-white","method":"machine","level":0},{"version":"colosseum","method":"machine","level":0},{"version":"xd","method":"machine","level":0},{"version":"black-2-white-2","method":"machine","level":0},{"version":"x-y","method":"machine","level":0},{"version":"omega-ruby-alpha-sapphire","method":"machine","level":0},{"version":"sun-moon","method":"machine","level":0},{"version":"ultra-sun-ultra-moon","method":"machine","level":0},{"version":"sword-shield","method":"machine","level":0}]},{"name":"ice-beam","versions":[{"version":"ruby-sapphire","method":"machine","level":0},{"version":"emerald","method":"machine","level":0},{"version":"firered-leafgreen","method":"machine","level":0},{"version":"diamond-pearl","method":"machine","level":0},{"version":"platinum","method":"machine","level":0},{"version":"heartgold-soulsilver","method":"machine","level":0},{"version":"black-white","method":"machine","level":0},{"version":"colosseum","method":"machine","level":0},{"version":"xd","method":"machine","level":0},{"version":"black-2-white-2","method":"machine","level":0},{"version":"x-y","method":"machine","level":0},{"version":"omega-ruby-alpha-sapphire","method":"machine","level":0},{"version":"sun-moon","method":"machine","level":0},{"version":"ultra-sun-ultra-moon","method":"machine","level":0},{"version":"sword-shield","method":"machine","level":0}]},{"name":"blizzard","versions":[{"version":"ruby-sapphire","method":"machine","level":0},{"version":"emerald","method":"machine","level":0},{"version":"firered-leafgreen","method":"machine","level":0},{"version":"diamond-pearl","method":"machine","level":0},{"version":"platinum","method":"machine","level":0},{"version":"heartgold-soulsilver","method":"machine","level":0},{"version":"black-white","method":"machine","level":0},{"version":"colosseum","method":"machine","level":0},{"version":"xd","method":"machine","level":0},{"version":"black-2-white-2","method":"machine","level":0},{"version":"x-y","method":"machine","level":0},{"version":"omega-ruby-alpha-sapphire","method":"machine","level":0},{"version":"sun-moon","method":"machine","level":0},{"version":"ultra-sun-ultra-moon","method":"machine","level":0},{"version":"sword-shield","method":"machine","level":0}]},{"name":"hyper-beam","versions":[{"version":"ruby-sapphire","method":"machine","level":0},{"version":"emerald","method":"machine","level":0},{"version":"firered-leafgreen","method":"machine","level":0},{"version":"diamond-pearl","method":"machine","level":0},{"version":"platinum","method":"machine","level":0},{"version":"heartgold-soulsilver","method":"machine","level":0},{"version":"black-white","method":"machine","level":0},{"version":"colosseum","method":"machine","level":0},{"version":"xd","method":"machine","level":0},{"version":"black-2-white-2","method":"machine","level":0},{"version":"x-y","method":"machine","level":0},{"version":"omega-ruby-alpha-sapphire","method":"machine","level":0},{"version":"sun-moon","method":"machine","level":0},{"version":"ultra-sun-ultra-moon","method":"machine","level":0},{"version":"sword-shield","method":"machine","level":0}]},{"name":"strength","versions":[{"version":"ruby-sapphire","method":"machine","level":0},{"version":"emerald","method":"machine","level":0},{"version":"firered-leafgreen","method":"machine","level":0},{"version":"diamond-pearl","method":"machine","level":0},{"version":"platinum","method":"machine","level":0},{"version":"heartgold-soulsilver","method":"machine","level":0},{"version":"black-white","method":"machine","level":0},{"version":"colosseum","method":"machine","level":0},{"version":"xd","method":"machine","level":0},{"version":"black-2-white-2","method":"machine","level":0},{"version":"x-y","method":"machine","level":0},{"version":"omega-ruby-alpha-sapphire","method":"machine","level":0}]},{"name":"earthquake","versions":[{"version":"ruby-sapphire","method":"machine","level":0},{"version":"emerald","method":"machine","level":0},{"version":"firered-leafgreen","method":"machine","level":0},{"version":"diamond-pearl","method":"machine","level":0},{"version":"platinum","method":"machine","level":0},{"version":"heartgold-soulsilver","method":"machine","level":0},{"version":"black-white","method":"machine","level":0},{"version":"colosseum","method":"machine","level":0},{"version":"xd","method":"machine","level":0},{"version":"black-2-white-2","method":"machine","level":0},{"version":"x-y","method":"machine","level":0},{"version":"omega-ruby-alpha-sapphire","method":"machine","level":0},{"version":"sun-moon","method":"machine","level":0},{"version":"ultra-sun-ultra-moon","method":"machine","level":0},{"version":"sword-shield","method":"machine","level":0}]},{"name":"toxic","versions":[{"version":"ruby-sapphire","method":"machine","level":0},{"version":"emerald","method":"machine","level":0},{"version":"firered-leafgreen","method":"machine","level":0},{"version":"diamond-pearl","method":"machine","level":0},{"version":"platinum","method":"machine","level":0},{"version":"heartgold-soulsilver","method":"machine","level":0},{"version":"black-white","method":"machine","level":0},{"version":"colosseum","method":"machine","level":0},{"version":"xd","method":"machine","level":0},{"version":"black-2-white-2","method":"machine","level":0},{"version":"x-y","method":"machine","level":0},{"version":"omega-ruby-alpha-sapphire","method":"machine","level":0},{"version":"sun-moon","method":"machine","level":0},{"version":"ultra-sun-ultra-moon","method":"machine","level":0}]},{"name":"mimic","versions":[{"version":"emerald","method":"tutor","level":0},{"version":"firered-leafgreen","method":"tutor","level":0},{"version":"xd","method":"tutor","level":0}]},{"name":"double-team","versions":[{"version":"ruby-sapphire","method":"machine","level":0},{"version":"emerald","method":"machine","level":0},{"version":"firered-leafgreen","method":"machine","level":0},{"version":"diamond-pearl","method":"machine","level":0},{"version":"platinum","method":"machine","level":0},{"version":"heartgold-soulsilver","method":"machine","level":0},{"version":"black-white","method":"machine","level":0},{"version":"colosseum","method":"machine","level":0},{"version":"xd","method":"machine","level":0},{"version":"black-2-white-2","method":"machine","level":0},{"version":"x-y","method":"machine","level":0},{"version":"omega-ruby-alpha-sapphire","method":"machine","level":0},{"version":"sun-moon","method":"machine","level":0},{"version":"ultra-sun-ultra-moon","method":"machine","level":0}]},{"name":"defense-curl","versions":[{"version":"emerald","method":"tutor","level":0}]},{"name":"self-destruct","versions":[{"version":"xd","method":"tutor","level":0},{"version":"sword-shield","method":"machine","level":0}]},{"name":"waterfall","versions":[{"version":"ruby-sapphire","method":"machine","level":0},{"version":"emerald","method":"machine","level":0},{"version":"firered-leafgreen","method":"machine","level":0},{"version":"diamond-pearl","method":"machine","level":0},{"version":"platinum","method":"machine","level":0},{"version":"heartgold-soulsilver","method":"machine","level":0},{"version":"black-white","method":"machine","level":0},{"version":"colosseum","method":"machine","level":0},{"version":"xd","method":"machine","level":0},{"version":"black-2-white-2","method":"machine","level":0},{"version":"x-y","method":"machine","level":0},{"version":"omega-ruby-alpha-sapphire","method":"machine","level":0},{"version":"sun-moon","method":"machine","level":0},{"version":"ultra-sun-ultra-moon","method":"machine","level":0},{"version":"sword-shield","method":"machine","level":0}]},{"name":"amnesia","versions":[{"version":"ruby-sapphire","method":"level-up","level":52},{"version":"emerald","method":"level-up","level":52},{"version":"firered-leafgreen","method":"level-up","level":52},{"version":"diamond-pearl","method":"level-up","level":37},{"version":"platinum","method":"level-up","level":37},{"version":"heartgold-soulsilver","method":"level-up","level":37},{"version":"black-white","method":"level-up","level":37},{"version":"colosseum","method":"level-up","level":52},{"version":"xd","method":"level-up","level":52},{"version":"black-2-white-2","method":"level-up","level":37},{"version":"x-y","method":"level-up","level":37},{"version":"omega-ruby-alpha-sapphire","method":"level-up","level":37},{"version":"sun-moon","method":"level-up","level":37},{"version":"ultra-sun-ultra-moon","method":"level-up","level":37},{"version":"sword-shield","method":"level-up","level":44},{"version":"sword-shield","method":"machine","level":0}]},{"name":"splash","versions":[{"version":"ruby-sapphire","method":"level-up","level":1},{"version":"emerald","method":"level-up","level":1},{"version":"firered-leafgreen","method":"level-up","level":1},{"version":"diamond-pearl","method":"level-up","level":1},{"version":"platinum","method":"level-up","level":1},{"version":"heartgold-soulsilver","method":"level-up","level":1},{"version":"black-white","method":"level-up","level":1},{"version":"colosseum","method":"level-up","level":1},{"version":"xd","method":"level-up","level":1},{"version":"black-2-white-2","method":"level-up","level":1},{"version":"x-y","method":"level-up","level":1},{"version":"omega-ruby-alpha-sapphire","method":"level-up","level":1},{"version":"sun-moon","method":"level-up","level":1},{"version":"ultra-sun-ultra-moon","method":"level-up","level":1},{"version":"sword-shield","method":"level-up","level":1}]},{"name":"rest","versions":[{"version":"ruby-sapphire","method":"level-up","level":37},{"version":"ruby-sapphire","method":"machine","level":0},{"version":"emerald","method":"level-up","level":37},{"version":"emerald","method":"machine","level":0},{"version":"firered-leafgreen","method":"level-up","level":37},{"version":"firered-leafgreen","method":"machine","level":0},{"version":"diamond-pearl","method":"level-up","level":27},{"version":"diamond-pearl","method":"machine","level":0},{"version":"platinum","method":"level-up","level":27},{"version":"platinum","method":"machine","level":0},{"version":"heartgold-soulsilver","method":"level-up","level":27},{"version":"heartgold-soulsilver","method":"machine","level":0},{"version":"black-white","method":"level-up","level":27},{"version":"black-white","method":"machine","level":0},{"version":"colosseum","method":"level-up","level":37},{"version":"colosseum","method":"machine","level":0},{"version":"xd","method":"level-up","level":37},{"version":"xd","method":"machine","level":0},{"version":"black-2-white-2","method":"level-up","level":27},{"version":"black-2-white-2","method":"machine","level":0},{"version":"x-y","method":"level-up","level":27},{"version":"x-y","method":"machine","level":0},{"version":"omega-ruby-alpha-sapphire","method":"level-up","level":25},{"version":"omega-ruby-alpha-sapphire","method":"machine","level":0},{"version":"sun-moon","method":"level-up","level":29},{"version":"sun-moon","method":"machine","level":0},{"version":"ultra-sun-ultra-moon","method":"level-up","level":29},{"version":"ultra-sun-ultra-moon","method":"machine","level":0},{"version":"sword-shield","method":"level-up","level":39},{"version":"sword-shield","method":"machine","level":0}]},{"name":"substitute","versions":[{"version":"emerald","method":"tutor","level":0},{"version":"firered-leafgreen","method":"tutor","level":0},{"version":"diamond-pearl","method":"machine","level":0},{"version":"platinum","method":"machine","level":0},{"version":"heartgold-soulsilver","method":"machine","level":0},{"version":"black-white","method":"machine","level":0},{"version":"xd","method":"tutor","level":0},{"version":"black-2-white-2","method":"machine","level":0},{"version":"x-y","method":"machine","level":0},{"version":"omega-ruby-alpha-sapphire","method":"machine","level":0},{"version":"sun-moon","method":"machine","level":0},{"version":"ultra-sun-ultra-moon","method":"machine","level":0},{"version":"sword-shield","method":"machine","level":0}]},{"name":"snore","versions":[{"version":"emerald","method":"tutor","level":0},{"version":"platinum","method":"tutor","level":0},{"version":"heartgold-soulsilver","method":"tutor","level":0},{"version":"black-2-white-2","method":"tutor","level":0},{"version":"omega-ruby-alpha-sapphire","method":"tutor","level":0},{"version":"ultra-sun-ultra-moon","method":"tutor","level":0},{"version":"sword-shield","method":"machine","level":0}]},{"name":"protect","versions":[{"version":"ruby-sapphire","method":"machine","level":0},{"version":"emerald","method":"machine","level":0},{"version":"firered-leafgreen","method":"machine","level":0},{"version":"diamond-pearl","method":"machine","level":0},{"version":"platinum","method":"machine","level":0},{"version":"heartgold-soulsilver","method":"machine","level":0},{"version":"black-white","method":"machine","level":0},{"version":"colosseum","method":"machine","level":0},{"version":"xd","method":"machine","level":0},{"version":"black-2-white-2","method":"machine","level":0},{"version":"x-y","method":"machine","level":0},{"version":"omega-ruby-alpha-sapphire","method":"machine","level":0},{"version":"sun-moon","method":"machine","level":0},{"version":"ultra-sun-ultra-moon","method":"machine","level":0},{"version":"sword-shield","method":"machine","level":0}]},{"name":"icy-wind","versions":[{"version":"emerald","method":"tutor","level":0},{"version":"platinum","method":"tutor","level":0},{"version":"heartgold-soulsilver","method":"tutor","level":0},{"version":"xd","method":"tutor","level":0},{"version":"black-2-white-2","method":"tutor","level":0},{"version":"omega-ruby-alpha-sapphire","method":"tutor","level":0},{"version":"ultra-sun-ultra-moon","method":"tutor","level":0},{"version":"sword-shield","method":"machine","level":0}]},{"name":"endure","versions":[{"version":"emerald","method":"tutor","level":0},{"version":"diamond-pearl","method":"machine","level":0},{"version":"platinum","method":"machine","level":0},{"version":"heartgold-soulsilver","method":"machine","level":0},{"version":"sword-shield","method":"machine","level":0}]},{"name":"rollout","versions":[{"version":"ruby-sapphire","method":"level-up","level":1},{"version":"ruby-sapphire","method":"level-up","level":14},{"version":"emerald","method":"level-up","level":1},{"version":"emerald","method":"level-up","level":14},{"version":"emerald","method":"tutor","level":0},{"version":"firered-leafgreen","method":"level-up","level":1},{"version":"firered-leafgreen","method":"level-up","level":14},{"version":"diamond-pearl","method":"level-up","level":1},{"version":"diamond-pearl","method":"level-up","level":11},{"version":"platinum","method":"level-up","level":1},{"version":"platinum","method":"level-up","level":11},{"version":"platinum","method":"tutor","level":0},{"version":"heartgold-soulsilver","method":"level-up","level":1},{"version":"heartgold-soulsilver","method":"level-up","level":11},{"version":"heartgold-soulsilver","method":"tutor","level":0},{"version":"black-white","method":"level-up","level":1},{"version":"black-white","method":"level-up","level":11},{"version":"colosseum","method":"level-up","level":1},{"version":"colosseum","method":"level-up","level":14},{"version":"xd","method":"level-up","level":1},{"version":"xd","method":"level-up","level":14},{"version":"black-2-white-2","method":"level-up","level":1},{"version":"black-2-white-2","method":"level-up","level":11},{"version":"x-y","method":"level-up","level":1},{"version":"x-y","method":"level-up","level":11},{"version":"omega-ruby-alpha-sapphire","method":"level-up","level":1},{"version":"omega-ruby-alpha-sapphire","method":"level-up","level":10},{"version":"sun-moon","method":"level-up","level":1},{"version":"sun-moon","method":"level-up","level":10},{"version":"ultra-sun-ultra-moon","method":"level-up","level":1},{"version":"ultra-sun-ultra-moon","method":"level-up","level":10}]},{"name":"swagger","versions":[{"version":"emerald","method":"tutor","level":0},{"version":"diamond-pearl","method":"machine","level":0},{"version":"platinum","method":"machine","level":0},{"version":"heartgold-soulsilver","method":"machine","level":0},{"version":"black-white","method":"machine","level":0},{"version":"xd","method":"tutor","level":0},{"version":"black-2-white-2","method":"machine","level":0},{"version":"x-y","method":"machine","level":0},{"version":"omega-ruby-alpha-sapphire","method":"machine","level":0},{"version":"sun-moon","method":"machine","level":0},{"version":"ultra-sun-ultra-moon","method":"machine","level":0}]},{"name":"attract","versions":[{"version":"ruby-sapphire","method":"machine","level":0},{"version":"emerald","method":"machine","level":0},{"version":"firered-leafgreen","method":"machine","level":0},{"version":"diamond-pearl","method":"machine","level":0},{"version":"platinum","method":"machine","level":0},{"version":"heartgold-soulsilver","method":"machine","level":0},{"version":"black-white","method":"machine","level":0},{"version":"colosseum","method":"machine","level":0},{"version":"xd","method":"machine","level":0},{"version":"black-2-white-2","method":"machine","level":0},{"version":"x-y","method":"machine","level":0},{"version":"omega-ruby-alpha-sapphire","method":"machine","level":0},{"version":"sun-moon","method":"machine","level":0},{"version":"ultra-sun-ultra-moon","method":"machine","level":0},{"version":"sword-shield","method":"machine","level":0}]},{"name":"sleep-talk","versions":[{"version":"emerald","method":"tutor","level":0},{"version":"diamond-pearl","method":"machine","level":0},{"version":"platinum","method":"machine","level":0},{"version":"heartgold-soulsilver","method":"machine","level":0},{"version":"black-2-white-2","method":"tutor","level":0},{"version":"x-y","method":"machine","level":0},{"version":"omega-ruby-alpha-sapphire","method":"machine","level":0},{"version":"sun-moon","method":"machine","level":0},{"version":"ultra-sun-ultra-moon","method":"machine","level":0},{"version":"sword-shield","method":"machine","level":0}]},{"name":"return","versions":[{"version":"ruby-sapphire","method":"machine","level":0},{"version":"emerald","method":"machine","level":0},{"version":"firered-leafgreen","method":"machine","level":0},{"version":"diamond-pearl","method":"machine","level":0},{"version":"platinum","method":"machine","level":0},{"version":"heartgold-soulsilver","method":"machine","level":0},{"version":"black-white","method":"machine","level":0},{"version":"colosseum","method":"machine","level":0},{"version":"xd","method":"machine","level":0},{"version":"black-2-white-2","method":"machine","level":0},{"version":"x-y","method":"machine","level":0},{"version":"omega-ruby-alpha-sapphire","method":"machine","level":0},{"version":"sun-moon","method":"machine","level":0},{"version":"ultra-sun-ultra-moon","method":"machine","level":0}]},{"name":"frustration","versions":[{"version":"ruby-sapphire","method":"machine","level":0},{"version":"emerald","method":"machine","level":0},{"version":"firered-leafgreen","method":"machine","level":0},{"version":"diamond-pearl","method":"machine","level":0},{"version":"platinum","method":"machine","level":0},{"version":"heartgold-soulsilver","method":"machine","level":0},{"version":"black-white","method":"machine","level":0},{"version":"colosseum","method":"machine","level":0},{"version":"xd","method":"machine","level":0},{"version":"black-2-white-2","method":"machine","level":0},{"version":"x-y","method":"machine","level":0},{"version":"omega-ruby-alpha-sapphire","method":"machine","level":0},{"version":"sun-moon","method":"machine","level":0},{"version":"ultra-sun-ultra-moon","method":"machine","level":0}]},{"name":"hidden-power","versions":[{"version":"ruby-sapphire","method":"machine","level":0},{"version":"emerald","method":"machine","level":0},{"version":"firered-leafgreen","method":"machine","level":0},{"version":"diamond-pearl","method":"machine","level":0},{"version":"platinum","method":"machine","level":0},{"version":"heartgold-soulsilver","method":"machine","level":0},{"version":"black-white","method":"machine","level":0},{"version":"colosseum","method":"machine","level":0},{"version":"xd","method":"machine","level":0},{"version":"black-2-white-2","method":"machine","level":0},{"version":"x-y","method":"machine","level":0},{"version":"omega-ruby-alpha-sapphire","method":"machine","level":0},{"version":"sun-moon","method":"machine","level":0},{"version":"ultra-sun-ultra-moon","method":"machine","level":0}]},{"name":"rain-dance","versions":[{"version":"ruby-sapphire","method":"machine","level":0},{"version":"emerald","method":"machine","level":0},{"version":"firered-leafgreen","method":"machine","level":0},{"version":"diamond-pearl","method":"machine","level":0},{"version":"platinum","method":"machine","level":0},{"version":"heartgold-soulsilver","method":"machine","level":0},{"version":"black-white","method":"machine","level":0},{"version":"colosseum","method":"machine","level":0},{"version":"xd","method":"machine","level":0},{"version":"black-2-white-2","method":"machine","level":0},{"version":"x-y","method":"machine","level":0},{"version":"omega-ruby-alpha-sapphire","method":"machine","level":0},{"version":"sun-moon","method":"machine","level":0},{"version":"ultra-sun-ultra-moon","method":"machine","level":0},{"version":"sword-shield","method":"machine","level":0}]},{"name":"rock-smash","versions":[{"version":"ruby-sapphire","method":"machine","level":0},{"version":"emerald","method":"machine","level":0},{"version":"firered-leafgreen","method":"machine","level":0},{"version":"diamond-pearl","method":"machine","level":0},{"version":"platinum","method":"machine","level":0},{"version":"heartgold-soulsilver","method":"machine","level":0},{"version":"black-white","method":"machine","level":0},{"version":"colosseum","method":"machine","level":0},{"version":"xd","method":"machine","level":0},{"version":"black-2-white-2","method":"machine","level":0},{"version":"x-y","method":"machine","level":0},{"version":"omega-ruby-alpha-sapphire","method":"machine","level":0}]},{"name":"whirlpool","versions":[{"version":"ruby-sapphire","method":"level-up","level":19},{"version":"emerald","method":"level-up","level":19},{"version":"firered-leafgreen","method":"level-up","level":19},{"version":"diamond-pearl","method":"level-up","level":14},{"version":"platinum","method":"level-up","level":14},{"version":"heartgold-soulsilver","method":"level-up","level":14},{"version":"heartgold-soulsilver","method":"machine","level":0},{"version":"black-white","method":"level-up","level":14},{"version":"colosseum","method":"level-up","level":19},{"version":"xd","method":"level-up","level":19},{"version":"black-2-white-2","method":"level-up","level":14},{"version":"x-y","method":"level-up","level":14},{"version":"omega-ruby-alpha-sapphire","method":"level-up","level":13},{"version":"sun-moon","method":"level-up","level":13},{"version":"ultra-sun-ultra-moon","method":"level-up","level":13},{"version":"sword-shield","method":"level-up","level":27},{"version":"sword-shield","method":"machine","level":0}]},{"name":"hail","versions":[{"version":"ruby-sapphire","method":"machine","level":0},{"version":"emerald","method":"machine","level":0},{"version":"firered-leafgreen","method":"machine","level":0},{"version":"diamond-pearl","method":"machine","level":0},{"version":"platinum","method":"machine","level":0},{"version":"heartgold-soulsilver","method":"machine","level":0},{"version":"black-white","method":"machine","level":0},{"version":"colosseum","method":"machine","level":0},{"version":"xd","method":"machine","level":0},{"version":"black-2-white-2","method":"machine","level":0},{"version":"x-y","method":"machine","level":0},{"version":"omega-ruby-alpha-sapphire","method":"machine","level":0},{"version":"sun-moon","method":"machine","level":0},{"version":"ultra-sun-ultra-moon","method":"machine","level":0},{"version":"sword-shield","method":"machine","level":0}]},{"name":"facade","versions":[{"version":"ruby-sapphire","method":"machine","level":0},{"version":"emerald","method":"machine","level":0},{"version":"firered-leafgreen","method":"machine","level":0},{"version":"diamond-pearl","method":"machine","level":0},{"version":"platinum","method":"machine","level":0},{"version":"heartgold-soulsilver","method":"machine","level":0},{"version":"black-white","method":"machine","level":0},{"version":"colosseum","method":"machine","level":0},{"version":"xd","method":"machine","level":0},{"version":"black-2-white-2","method":"machine","level":0},{"version":"x-y","method":"machine","level":0},{"version":"omega-ruby-alpha-sapphire","method":"machine","level":0},{"version":"sun-moon","method":"machine","level":0},{"version":"ultra-sun-ultra-moon","method":"machine","level":0},{"version":"sword-shield","method":"machine","level":0}]},{"name":"secret-power","versions":[{"version":"ruby-sapphire","method":"machine","level":0},{"version":"emerald","method":"machine","level":0},{"version":"firered-leafgreen","method":"machine","level":0},{"version":"diamond-pearl","method":"machine","level":0},{"version":"platinum","method":"machine","level":0},{"version":"heartgold-soulsilver","method":"machine","level":0},{"version":"colosseum","method":"machine","level":0},{"version":"xd","method":"machine","level":0},{"version":"omega-ruby-alpha-sapphire","method":"machine","level":0}]},{"name":"dive","versions":[{"version":"ruby-sapphire","method":"machine","level":0},{"version":"emerald","method":"machine","level":0},{"version":"firered-leafgreen","method":"machine","level":0},{"version":"diamond-pearl","method":"level-up","level":46},{"version":"platinum","method":"level-up","level":46},{"version":"platinum","method":"tutor","level":0},{"version":"heartgold-soulsilver","method":"level-up","level":46},{"version":"heartgold-soulsilver","method":"tutor","level":0},{"version":"black-white","method":"level-up","level":46},{"version":"black-white","method":"machine","level":0},{"version":"colosseum","method":"machine","level":0},{"version":"xd","method":"machine","level":0},{"version":"black-2-white-2","method":"level-up","level":46},{"version":"black-2-white-2","method":"machine","level":0},{"version":"x-y","method":"level-up","level":46},{"version":"omega-ruby-alpha-sapphire","method":"level-up","level":44},{"version":"omega-ruby-alpha-sapphire","method":"machine","level":0},{"version":"sun-moon","method":"level-up","level":44},{"version":"ultra-sun-ultra-moon","method":"level-up","level":44},{"version":"sword-shield","method":"level-up","level":30},{"version":"sword-shield","method":"machine","level":0}]},{"name":"hyper-voice","versions":[{"version":"black-2-white-2","method":"tutor","level":0},{"version":"omega-ruby-alpha-sapphire","method":"tutor","level":0},{"version":"ultra-sun-ultra-moon","method":"tutor","level":0},{"version":"sword-shield","method":"machine","level":0}]},{"name":"astonish","versions":[{"version":"ruby-sapphire","method":"level-up","level":23},{"version":"emerald","method":"level-up","level":23},{"version":"firered-leafgreen","method":"level-up","level":23},{"version":"diamond-pearl","method":"level-up","level":17},{"version":"platinum","method":"level-up","level":17},{"version":"heartgold-soulsilver","method":"level-up","level":17},{"version":"black-white","method":"level-up","level":17},{"version":"colosseum","method":"level-up","level":23},{"version":"xd","method":"level-up","level":23},{"version":"black-2-white-2","method":"level-up","level":17},{"version":"x-y","method":"level-up","level":17},{"version":"omega-ruby-alpha-sapphire","method":"level-up","level":16},{"version":"sun-moon","method":"level-up","level":16},{"version":"ultra-sun-ultra-moon","method":"level-up","level":16},{"version":"sword-shield","method":"level-up","level":1}]},{"name":"weather-ball","versions":[{"version":"sword-shield","method":"machine","level":0}]},{"name":"rock-tomb","versions":[{"version":"ruby-sapphire","method":"machine","level":0},{"version":"emerald","method":"machine","level":0},{"version":"firered-leafgreen","method":"machine","level":0},{"version":"diamond-pearl","method":"machine","level":0},{"version":"platinum","method":"machine","level":0},{"version":"heartgold-soulsilver","method":"machine","level":0},{"version":"black-white","method":"machine","level":0},{"version":"colosseum","method":"machine","level":0},{"version":"xd","method":"machine","level":0},{"version":"black-2-white-2","method":"machine","level":0},{"version":"x-y","method":"machine","level":0},{"version":"omega-ruby-alpha-sapphire","method":"machine","level":0},{"version":"sun-moon","method":"machine","level":0},{"version":"ultra-sun-ultra-moon","method":"machine","level":0},{"version":"sword-shield","method":"machine","level":0}]},{"name":"water-spout","versions":[{"version":"ruby-sapphire","method":"level-up","level":44},{"version":"emerald","method":"level-up","level":44},{"version":"firered-leafgreen","method":"level-up","level":44},{"version":"diamond-pearl","method":"level-up","level":34},{"version":"platinum","method":"level-up","level":34},{"version":"heartgold-soulsilver","method":"level-up","level":34},{"version":"black-white","method":"level-up","level":34},{"version":"colosseum","method":"level-up","level":44},{"version":"xd","method":"level-up","level":44},{"version":"black-2-white-2","method":"level-up","level":34},{"version":"x-y","method":"level-up","level":34},{"version":"omega-ruby-alpha-sapphire","method":"level-up","level":33},{"version":"sun-moon","method":"level-up","level":33},{"version":"ultra-sun-ultra-moon","method":"level-up","level":33},{"version":"sword-shield","method":"level-up","level":54}]},{"name":"block","versions":[{"version":"heartgold-soulsilver","method":"tutor","level":0},{"version":"black-2-white-2","method":"tutor","level":0},{"version":"omega-ruby-alpha-sapphire","method":"tutor","level":0},{"version":"ultra-sun-ultra-moon","method":"tutor","level":0}]},{"name":"bounce","versions":[{"version":"diamond-pearl","method":"level-up","level":54},{"version":"platinum","method":"level-up","level":54},{"version":"platinum","method":"tutor","level":0},{"version":"heartgold-soulsilver","method":"level-up","level":54},{"version":"heartgold-soulsilver","method":"tutor","level":0},{"version":"black-white","method":"level-up","level":54},{"version":"black-2-white-2","method":"level-up","level":54},{"version":"black-2-white-2","method":"tutor","level":0},{"version":"x-y","method":"level-up","level":54},{"version":"omega-ruby-alpha-sapphire","method":"level-up","level":51},{"version":"omega-ruby-alpha-sapphire","method":"tutor","level":0},{"version":"sun-moon","method":"level-up","level":51},{"version":"ultra-sun-ultra-moon","method":"level-up","level":51},{"version":"ultra-sun-ultra-moon","method":"tutor","level":0},{"version":"sword-shield","method":"level-up","level":33},{"version":"sword-shield","method":"machine","level":0}]},{"name":"water-pulse","versions":[{"version":"ruby-sapphire","method":"level-up","level":28},{"version":"ruby-sapphire","method":"machine","level":0},{"version":"emerald","method":"level-up","level":28},{"version":"emerald","method":"machine","level":0},{"version":"firered-leafgreen","method":"level-up","level":28},{"version":"firered-leafgreen","method":"machine","level":0},{"version":"diamond-pearl","method":"level-up","level":21},{"version":"diamond-pearl","method":"machine","level":0},{"version":"platinum","method":"level-up","level":21},{"version":"platinum","method":"machine","level":0},{"version":"heartgold-soulsilver","method":"level-up","level":21},{"version":"heartgold-soulsilver","method":"machine","level":0},{"version":"black-white","method":"level-up","level":21},{"version":"colosseum","method":"level-up","level":28},{"version":"colosseum","method":"machine","level":0},{"version":"xd","method":"level-up","level":28},{"version":"xd","method":"machine","level":0},{"version":"black-2-white-2","method":"level-up","level":21},{"version":"x-y","method":"level-up","level":21},{"version":"omega-ruby-alpha-sapphire","method":"level-up","level":19},{"version":"omega-ruby-alpha-sapphire","method":"tutor","level":0},{"version":"sun-moon","method":"level-up","level":19},{"version":"ultra-sun-ultra-moon","method":"level-up","level":19},{"version":"ultra-sun-ultra-moon","method":"tutor","level":0},{"version":"sword-shield","method":"level-up","level":18}]},{"name":"brine","versions":[{"version":"diamond-pearl","method":"level-up","level":31},{"version":"diamond-pearl","method":"machine","level":0},{"version":"platinum","method":"level-up","level":31},{"version":"platinum","method":"machine","level":0},{"version":"heartgold-soulsilver","method":"level-up","level":31},{"version":"heartgold-soulsilver","method":"machine","level":0},{"version":"black-white","method":"level-up","level":31},{"version":"black-2-white-2","method":"level-up","level":31},{"version":"x-y","method":"level-up","level":31},{"version":"omega-ruby-alpha-sapphire","method":"level-up","level":29},{"version":"sun-moon","method":"level-up","level":25},{"version":"ultra-sun-ultra-moon","method":"level-up","level":25},{"version":"sword-shield","method":"level-up","level":24},{"version":"sword-shield","method":"machine","level":0}]},{"name":"natural-gift","versions":[{"version":"diamond-pearl","method":"machine","level":0},{"version":"platinum","method":"machine","level":0},{"version":"heartgold-soulsilver","method":"machine","level":0}]},{"name":"giga-impact","versions":[{"version":"diamond-pearl","method":"machine","level":0},{"version":"platinum","method":"machine","level":0},{"version":"heartgold-soulsilver","method":"machine","level":0},{"version":"black-white","method":"machine","level":0},{"version":"black-2-white-2","method":"machine","level":0},{"version":"x-y","method":"machine","level":0},{"version":"omega-ruby-alpha-sapphire","method":"machine","level":0},{"version":"sun-moon","method":"machine","level":0},{"version":"ultra-sun-ultra-moon","method":"machine","level":0},{"version":"sword-shield","method":"machine","level":0}]},{"name":"avalanche","versions":[{"version":"diamond-pearl","method":"machine","level":0},{"version":"platinum","method":"machine","level":0},{"version":"heartgold-soulsilver","method":"machine","level":0},{"version":"sword-shield","method":"machine","level":0}]},{"name":"zen-headbutt","versions":[{"version":"black-2-white-2","method":"tutor","level":0},{"version":"omega-ruby-alpha-sapphire","method":"tutor","level":0},{"version":"ultra-sun-ultra-moon","method":"tutor","level":0},{"version":"sword-shield","method":"machine","level":0}]},{"name":"iron-head","versions":[{"version":"platinum","method":"tutor","level":0},{"version":"heartgold-soulsilver","method":"tutor","level":0},{"version":"black-2-white-2","method":"tutor","level":0},{"version":"omega-ruby-alpha-sapphire","method":"tutor","level":0},{"version":"ultra-sun-ultra-moon","method":"tutor","level":0},{"version":"sword-shield","method":"machine","level":0}]},{"name":"captivate","versions":[{"version":"diamond-pearl","method":"machine","level":0},{"version":"platinum","method":"machine","level":0},{"version":"heartgold-soulsilver","method":"machine","level":0}]},{"name":"heavy-slam","versions":[{"version":"black-white","method":"level-up","level":70},{"version":"black-2-white-2","method":"level-up","level":70},{"version":"x-y","method":"level-up","level":70},{"version":"omega-ruby-alpha-sapphire","method":"level-up","level":1},{"version":"omega-ruby-alpha-sapphire","method":"level-up","level":65},{"version":"sun-moon","method":"level-up","level":1},{"version":"sun-moon","method":"level-up","level":65},{"version":"ultra-sun-ultra-moon","method":"level-up","level":1},{"version":"ultra-sun-ultra-moon","method":"level-up","level":65},{"version":"sword-shield","method":"level-up","level":21},{"version":"sword-shield","method":"machine","level":0}]},{"name":"soak","versions":[{"version":"sun-moon","method":"level-up","level":1},{"version":"ultra-sun-ultra-moon","method":"level-up","level":1},{"version":"sword-shield","method":"level-up","level":1}]},{"name":"round","versions":[{"version":"black-white","method":"machine","level":0},{"version":"black-2-white-2","method":"machine","level":0},{"version":"x-y","method":"machine","level":0},{"version":"omega-ruby-alpha-sapphire","method":"machine","level":0},{"version":"sun-moon","method":"machine","level":0},{"version":"ultra-sun-ultra-moon","method":"machine","level":0},{"version":"sword-shield","method":"machine","level":0}]},{"name":"echoed-voice","versions":[{"version":"black-white","method":"machine","level":0},{"version":"black-2-white-2","method":"machine","level":0},{"version":"x-y","method":"machine","level":0},{"version":"omega-ruby-alpha-sapphire","method":"machine","level":0},{"version":"sun-moon","method":"machine","level":0},{"version":"ultra-sun-ultra-moon","method":"machine","level":0}]},{"name":"scald","versions":[{"version":"black-white","method":"machine","level":0},{"version":"black-2-white-2","method":"machine","level":0},{"version":"x-y","method":"machine","level":0},{"version":"omega-ruby-alpha-sapphire","method":"machine","level":0},{"version":"sun-moon","method":"machine","level":0},{"version":"ultra-sun-ultra-moon","method":"machine","level":0},{"version":"sword-shield","method":"machine","level":0}]},{"name":"bulldoze","versions":[{"version":"black-white","method":"machine","level":0},{"version":"black-2-white-2","method":"machine","level":0},{"version":"x-y","method":"machine","level":0},{"version":"omega-ruby-alpha-sapphire","method":"machine","level":0},{"version":"sun-moon","method":"machine","level":0},{"version":"ultra-sun-ultra-moon","method":"machine","level":0},{"version":"sword-shield","method":"machine","level":0}]},{"name":"noble-roar","versions":[{"version":"sun-moon","method":"level-up","level":1},{"version":"ultra-sun-ultra-moon","method":"level-up","level":1},{"version":"sword-shield","method":"level-up","level":1}]},{"name":"confide","versions":[{"version":"x-y","method":"machine","level":0},{"version":"omega-ruby-alpha-sapphire","method":"machine","level":0},{"version":"sun-moon","method":"machine","level":0},{"version":"ultra-sun-ultra-moon","method":"machine","level":0}]},{"name":"liquidation","versions":[{"version":"ultra-sun-ultra-moon","method":"tutor","level":0},{"version":"sword-shield","method":"machine","level":0}]},{"name":"body-press","versions":[{"version":"sword-shield","method":"machine","level":0}]},{"name":"steel-roller","versions":[{"version":"sword-shield","method":"tutor","level":0}]}]}